bucketeer/__init__.py
bucketeer/bucketeer.py
bucketeer/version.py
bucketeer/connections/__init__.py
bucketeer/connections/local.py
bucketeer/connections/redis_connection.py
bucketeer/exceptions/__init__.py
bucketeer/objects/__init__.py
bucketeer/objects/connections.py
bucketeer/objects/key.py
bucketeer/objects/returned_key.py
bucketeer/objects/service.py
bucketeer-0.1.8.dist-info/METADATA
bucketeer-0.1.8.dist-info/WHEEL
bucketeer-0.1.8.dist-info/top_level.txt
bucketeer-0.1.8.dist-info/RECORD
